otquickmodule/KernelHerding.py
otquickmodule/QuadratureWeighting.py
otquickmodule/__init__.py
test/test_KernelHerding.py
test/test_QuadratureWeighting.py
otquickmodule-0.0.1.dist-info/LICENSE
otquickmodule-0.0.1.dist-info/METADATA
otquickmodule-0.0.1.dist-info/WHEEL
otquickmodule-0.0.1.dist-info/top_level.txt
otquickmodule-0.0.1.dist-info/RECORD
