Metadata-Version: 2.1
Name: otquickmodule
Version: 0.0.1
Summary: This repository is a tutorial for quick Python packaging
Home-page: https://github.com/efekhari27/otquickmodule
Author: Elias Fekhari
Author-email: elias.fekhari@edf.fr
License: GPLv3+
Keywords: OpenTURNS,KernelHerding
Classifier: Programming Language :: Python :: 3
Classifier: License :: OSI Approved :: GNU General Public License v3 or later (GPLv3+)
Classifier: Intended Audience :: Science/Research
Classifier: Topic :: Software Development
Classifier: Topic :: Scientific/Engineering
License-File: LICENSE
Requires-Dist: numpy
Requires-Dist: scipy
Requires-Dist: openturns (>=1.17)
